{
	"schemaVersion": 1,
	"id": "arcanus",
	"version": "${version}",
	"name": "Arcanus",
	"description": "A magic mod with a magic system inspired by Wynncraft and Electroblob's Wizardry",
	"authors": [
		"ComradeCammie"
	],
	"contact": {
		"homepage": "https://www.curseforge.com/minecraft/mc-mods/arcanus",
		"sources": "https://github.com/CammiePone/Arcanus"
	},
	"license": "Custom License",
	"icon": "assets/arcanus/icon.png",
	"environment": "*",
	"entrypoints": {
		"main": [
			"dev.cammiescorner.arcanus.Arcanus"
		],
		"client": [
			"dev.cammiescorner.arcanus.client.ArcanusClient"
		],
		"modmenu": [
			"dev.cammiescorner.arcanus.core.integration.ArcanusModMenu"
		]
	},
	"mixins": [
		"arcanus.mixins.json"
	],
	"accessWidener": "META-INF/arcanus.accesswidener",
	"depends": {
		"fabricloader": ">=0.11.0-",
		"fabric": "*",
		"minecraft": "1.17.x",
		"cloth-config2": ">=5.0.38",
		"trinkets": ">=3.0.4"
	}
}
